flask_fs/__about__.py
flask_fs/__init__.py
flask_fs/errors.py
flask_fs/files.py
flask_fs/images.py
flask_fs/mongo.py
flask_fs/signals.py
flask_fs/storage.py
flask_fs/views.py
flask_fs/backends/__init__.py
flask_fs/backends/gridfs.py
flask_fs/backends/local.py
flask_fs/backends/mock.py
flask_fs/backends/s3.py
flask_fs/backends/swift.py
flask_fs-0.6.1.dist-info/DESCRIPTION.rst
flask_fs-0.6.1.dist-info/METADATA
flask_fs-0.6.1.dist-info/RECORD
flask_fs-0.6.1.dist-info/WHEEL
flask_fs-0.6.1.dist-info/entry_points.txt
flask_fs-0.6.1.dist-info/metadata.json
flask_fs-0.6.1.dist-info/top_level.txt
tests/__init__.py
tests/conftest.py
tests/test_backend_mixin.py
tests/test_config.py
tests/test_files.py
tests/test_gridfs_backend.py
tests/test_local_backend.py
tests/test_mongoengine.py
tests/test_s3_backend.py
tests/test_storage.py
tests/test_swift_backend.py
tests/test_views.py
