Metadata-Version: 2.0
Name: flask-fs
Version: 0.6.1
Summary: Simple and easy file storages for Flask
Home-page: https://github.com/noirbizarre/flask-fs
Author: Axel Haustant
Author-email: noirbizarre@gmail.com
License: MIT
Platform: UNKNOWN
Classifier: Development Status :: 5 - Production/Stable
Classifier: Programming Language :: Python
Classifier: Environment :: Web Environment
Classifier: Operating System :: OS Independent
Classifier: Intended Audience :: Developers
Classifier: Topic :: System :: Software Distribution
Classifier: Programming Language :: Python
Classifier: Programming Language :: Python :: 2
Classifier: Programming Language :: Python :: 2.7
Classifier: Programming Language :: Python :: 3
Classifier: Programming Language :: Python :: 3.4
Classifier: Programming Language :: Python :: 3.5
Classifier: Programming Language :: Python :: 3.6
Classifier: Programming Language :: Python :: Implementation :: CPython
Classifier: Programming Language :: Python :: Implementation :: PyPy
Classifier: Topic :: Internet :: WWW/HTTP :: Dynamic Content
Classifier: Topic :: Software Development :: Libraries :: Python Modules
Classifier: License :: OSI Approved :: MIT License
Requires-Dist: flask
Requires-Dist: python-dateutil
Requires-Dist: six
Provides-Extra: all
Requires-Dist: boto3 (>=1.4.5); extra == 'all'
Requires-Dist: pymongo (>=3.0); extra == 'all'
Requires-Dist: python-swiftclient; extra == 'all'
Provides-Extra: ci
Requires-Dist: boto3 (>=1.4.5); extra == 'ci'
Requires-Dist: flake8 (==3.5.0); extra == 'ci'
Requires-Dist: flask-mongoengine (==0.9.5); extra == 'ci'
Requires-Dist: invoke (>=0.22.1); extra == 'ci'
Requires-Dist: pillow; extra == 'ci'
Requires-Dist: pymongo (>=3.0); extra == 'ci'
Requires-Dist: pytest (==3.4.2); extra == 'ci'
Requires-Dist: pytest-cov (==2.5.1); extra == 'ci'
Requires-Dist: pytest-faker (==2.0.0); extra == 'ci'
Requires-Dist: pytest-flask (==0.10.0); extra == 'ci'
Requires-Dist: pytest-mock (==1.7.1); extra == 'ci'
Requires-Dist: pytest-sugar (==0.9.1); extra == 'ci'
Requires-Dist: python-swiftclient; extra == 'ci'
Provides-Extra: dev
Requires-Dist: alabaster (==0.7.10); extra == 'dev'
Requires-Dist: boto3 (>=1.4.5); extra == 'dev'
Requires-Dist: boto3 (>=1.4.5); extra == 'dev'
Requires-Dist: flake8 (==3.5.0); extra == 'dev'
Requires-Dist: flask-mongoengine (==0.9.5); extra == 'dev'
Requires-Dist: flask-mongoengine (==0.9.5); extra == 'dev'
Requires-Dist: invoke (==0.22.1); extra == 'dev'
Requires-Dist: pillow; extra == 'dev'
Requires-Dist: pillow; extra == 'dev'
Requires-Dist: pymongo (>=3.0); extra == 'dev'
Requires-Dist: pymongo (>=3.0); extra == 'dev'
Requires-Dist: pytest (==3.4.2); extra == 'dev'
Requires-Dist: pytest-cov (==2.5.1); extra == 'dev'
Requires-Dist: pytest-faker (==2.0.0); extra == 'dev'
Requires-Dist: pytest-flask (==0.10.0); extra == 'dev'
Requires-Dist: pytest-mock (==1.7.1); extra == 'dev'
Requires-Dist: pytest-sugar (==0.9.1); extra == 'dev'
Requires-Dist: python-swiftclient; extra == 'dev'
Requires-Dist: python-swiftclient; extra == 'dev'
Requires-Dist: sphinx (==1.7.1); extra == 'dev'
Requires-Dist: tox; extra == 'dev'
Provides-Extra: doc
Requires-Dist: alabaster (==0.7.10); extra == 'doc'
Requires-Dist: boto3 (>=1.4.5); extra == 'doc'
Requires-Dist: flask-mongoengine (==0.9.5); extra == 'doc'
Requires-Dist: pillow; extra == 'doc'
Requires-Dist: pymongo (>=3.0); extra == 'doc'
Requires-Dist: python-swiftclient; extra == 'doc'
Requires-Dist: sphinx (==1.7.1); extra == 'doc'
Provides-Extra: gridfs
Requires-Dist: pymongo (>=3.0); extra == 'gridfs'
Provides-Extra: qa
Requires-Dist: boto3 (>=1.4.5); extra == 'qa'
Requires-Dist: flask-mongoengine (==0.9.5); extra == 'qa'
Requires-Dist: pillow; extra == 'qa'
Requires-Dist: pymongo (>=3.0); extra == 'qa'
Requires-Dist: pytest (==3.4.2); extra == 'qa'
Requires-Dist: pytest-faker (==2.0.0); extra == 'qa'
Requires-Dist: pytest-flask (==0.10.0); extra == 'qa'
Requires-Dist: pytest-mock (==1.7.1); extra == 'qa'
Requires-Dist: pytest-sugar (==0.9.1); extra == 'qa'
Requires-Dist: python-swiftclient; extra == 'qa'
Provides-Extra: s3
Requires-Dist: boto3 (>=1.4.5); extra == 's3'
Provides-Extra: swift
Requires-Dist: python-swiftclient; extra == 'swift'
Provides-Extra: test
Requires-Dist: boto3 (>=1.4.5); extra == 'test'
Requires-Dist: flask-mongoengine (==0.9.5); extra == 'test'
Requires-Dist: pillow; extra == 'test'
Requires-Dist: pymongo (>=3.0); extra == 'test'
Requires-Dist: pytest (==3.4.2); extra == 'test'
Requires-Dist: pytest-faker (==2.0.0); extra == 'test'
Requires-Dist: pytest-flask (==0.10.0); extra == 'test'
Requires-Dist: pytest-mock (==1.7.1); extra == 'test'
Requires-Dist: pytest-sugar (==0.9.1); extra == 'test'
Requires-Dist: python-swiftclient; extra == 'test'
